{
  "feature_names": [
    "anisotropy",
    "crest_factor",
    "disp_kurtosis",
    "disp_max",
    "disp_mean",
    "disp_median",
    "disp_p95",
    "disp_skew",
    "disp_std",
    "dominant_freq",
    "energy_mean",
    "energy_std",
    "energy_trend",
    "frame_variance",
    "impulse_factor",
    "min_interatomic_dist",
    "msd_final",
    "msd_mean",
    "msd_slope",
    "msd_std",
    "rdf_first_peak_height",
    "rdf_first_peak_pos",
    "rms_velocity",
    "spectral_entropy",
    "spectral_peak_ratio",
    "vacf_initial_decay",
    "vacf_zero_crossing"
  ],
  "n_aimd_windows": 1648,
  "n_mlff_windows": 835,
  "aimd_anomaly_rate_l12": 0.03944174757281554,
  "mlff_anomaly_rate_l12": 1.0,
  "aimd_anomaly_rate_all3": 0.35365853658536583,
  "mlff_anomaly_rate_all3": 1.0,
  "lstm_threshold": 0.20416584610939026,
  "window_size": 50,
  "stride": 10
}